dhanhq/__init__.py
dhanhq/dhanhq.py
dhanhq/marketfeed.py
dhanhq-1.3.3.dist-info/LICENSE
dhanhq-1.3.3.dist-info/METADATA
dhanhq-1.3.3.dist-info/WHEEL
dhanhq-1.3.3.dist-info/top_level.txt
dhanhq-1.3.3.dist-info/RECORD
