Metadata-Version: 2.1
Name: dhanhq
Version: 1.3.3
Summary: The official Python client for communicating with the Dhan API
Home-page: 
Author: Dhan
Author-email: dhan-oss@dhan.co
License: MIT LICENSE
License-File: LICENSE
Requires-Dist: pandas>=1.4.3
Requires-Dist: requests>=2.28.1
Requires-Dist: websockets>=11.0.1
Requires-Dist: pyOpenSSL>=20.0.1
